CHANGES.txt
README.txt
bootstrap.py
buildout.cfg
setup.py
parts/i18n/configure.zcml
src/eggserver/__init__.py
src/eggserver/configure.zcml
src/eggserver/eggsrv.py
src/eggserver/ftesting.zcml
src/eggserver/header.txt
src/eggserver/parse_pkg_info.py
src/eggserver/testing.py
src/eggserver/util.py
src/eggserver.egg-info/PKG-INFO
src/eggserver.egg-info/SOURCES.txt
src/eggserver.egg-info/dependency_links.txt
src/eggserver.egg-info/entry_points.txt
src/eggserver.egg-info/not-zip-safe
src/eggserver.egg-info/paster_plugins.txt
src/eggserver.egg-info/requires.txt
src/eggserver.egg-info/top_level.txt
src/eggserver/eggsrv_templates/index.pt
src/eggserver/eggsrv_templates/master.pt
src/eggserver/eggsrv_templates/metadata.pt
src/eggserver/eggsrv_templates/showpackage.pt
src/eggserver/eggsrv_templates/simple.pt
src/eggserver/static/eggsrv.css
src/eggserver/static/eggsrv.jpg
src/eggserver/static/logo.gif
src/haufe.eggserver.egg-info/PKG-INFO
src/haufe.eggserver.egg-info/SOURCES.txt
src/haufe.eggserver.egg-info/dependency_links.txt
src/haufe.eggserver.egg-info/entry_points.txt
src/haufe.eggserver.egg-info/not-zip-safe
src/haufe.eggserver.egg-info/requires.txt
src/haufe.eggserver.egg-info/top_level.txt