Metadata-Version: 1.0
Name: haufe.eggserver
Version: 0.2.6
Summary: A small PyPI replacement based on a local distribution directory (implemented using GROK)
Home-page: UNKNOWN
Author: Andreas Jung
Author-email: info@zopyx.com
License: ZPL 2.1
Platform: UNKNOWN
